missing_data_cli_76.py
nishant_miss_data_76.py
nishant_miss_data_76-1.2.1.dist-info/LICENSE
nishant_miss_data_76-1.2.1.dist-info/METADATA
nishant_miss_data_76-1.2.1.dist-info/WHEEL
nishant_miss_data_76-1.2.1.dist-info/entry_points.txt
nishant_miss_data_76-1.2.1.dist-info/top_level.txt
nishant_miss_data_76-1.2.1.dist-info/RECORD
