Metadata-Version: 2.1
Name: nishant-miss-data-76
Version: 1.2.1
Summary: Handle Missing Data
Home-page: https://github.com/nishu195/nishant_miss_data_76
Author: Nishant Goel
Author-email: ngoel_be17@thapar.edu
License: UNKNOWN
Keywords: command-line,Missing-Data
Platform: UNKNOWN
Classifier: Programming Language :: Python :: 3
Classifier: License :: OSI Approved :: MIT License
Classifier: Operating System :: OS Independent
Requires-Python: >=3.6
Requires-Dist: numpy
Requires-Dist: pandas
